LICENSE
requests_counter/__init__.py
requests_counter/_redismodule.py
requests_counter/api.py
requests_counter/example.py
requests_counter/reqcounter.py
requests_counter-2.0.1.dist-info/LICENSE
requests_counter-2.0.1.dist-info/WHEEL
requests_counter-2.0.1.dist-info/METADATA
requests_counter-2.0.1.dist-info/RECORD
