Metadata-Version: 2.1
Name: requests-counter
Version: 2.0.1
Summary: A tool to monitor the number of HTTP requests through an _apiKey_ in the HTTP Header.
Home-page: https://github.com/Arfius/requests-counter
License: MIT
Keywords: monitor,api,request,api_key,origin,source
Author: Alfonso Farruggia
Requires-Python: >=3.7,<4.0
Classifier: License :: OSI Approved :: MIT License
Classifier: Programming Language :: Python :: 3
Classifier: Programming Language :: Python :: 3.7
Classifier: Programming Language :: Python :: 3.8
Classifier: Programming Language :: Python :: 3.9
Requires-Dist: aioredis (>=1.3.1,<2.0.0)
Requires-Dist: asyncio (>=3.4.3,<4.0.0)
Requires-Dist: fastapi (>=0.63.0,<0.64.0)
Requires-Dist: flake8 (>=3.8.4,<4.0.0)
Requires-Dist: pytest (>=6.2.2,<7.0.0)
Requires-Dist: pytest-asyncio (>=0.14.0,<0.15.0)
Project-URL: Bug Tracker, https://github.com/Arfius/requests-counter/issues
Project-URL: Repository, https://github.com/Arfius/requests-counter
